{
    "key": "group_5d36e0cfdfff1",
    "title": "Bristol Dates",
    "fields": [
        {
            "key": "field_5d36e0cfe2ae6",
            "label": "Dates",
            "name": "dates_bristol",
            "type": "repeater",
            "instructions": "",
            "required": 0,
            "conditional_logic": 0,
            "wrapper": {
                "width": "",
                "class": "",
                "id": ""
            },
            "collapsed": "",
            "min": 0,
            "max": 0,
            "layout": "table",
            "button_label": "",
            "sub_fields": [
                {
                    "key": "field_5d36e0cfe48b7",
                    "label": "Date",
                    "name": "date",
                    "type": "date_picker",
                    "instructions": "",
                    "required": 1,
                    "conditional_logic": 0,
                    "wrapper": {
                        "width": "",
                        "class": "",
                        "id": ""
                    },
                    "display_format": "Y-m-d",
                    "return_format": "Y-m-d",
                    "first_day": 1
                },
                {
                    "key": "field_5d36e0cfe4c76",
                    "label": "Time",
                    "name": "time",
                    "type": "select",
                    "instructions": "",
                    "required": 1,
                    "conditional_logic": 0,
                    "wrapper": {
                        "width": "",
                        "class": "",
                        "id": ""
                    },
                    "choices": {
                        "matinee": "Matinee",
                        "evening": "Evening"
                    },
                    "default_value": [
                        "Matinee"
                    ],
                    "allow_null": 0,
                    "multiple": 0,
                    "ui": 0,
                    "return_format": "value",
                    "ajax": 0,
                    "placeholder": ""
                },
                {
                    "key": "field_5d36e2584ec70",
                    "label": "Show URL",
                    "name": "show_url",
                    "type": "url",
                    "instructions": "",
                    "required": 0,
                    "conditional_logic": 0,
                    "wrapper": {
                        "width": "",
                        "class": "",
                        "id": ""
                    },
                    "default_value": "",
                    "placeholder": ""
                },
                {
                    "key": "field_5d36e1212a55b",
                    "label": "Availablity",
                    "name": "availablity",
                    "type": "select",
                    "instructions": "",
                    "required": 1,
                    "conditional_logic": 0,
                    "wrapper": {
                        "width": "",
                        "class": "",
                        "id": ""
                    },
                    "choices": {
                        "available": "Available",
                        "goodseats": "Good Seats",
                        "limited": "Limited",
                        "unavailable": "Unavailable"
                    },
                    "default_value": [
                        "Available"
                    ],
                    "allow_null": 0,
                    "multiple": 0,
                    "ui": 0,
                    "return_format": "value",
                    "ajax": 0,
                    "placeholder": ""
                }
            ]
        }
    ],
    "location": [
        [
            {
                "param": "options_page",
                "operator": "==",
                "value": "acf-options"
            }
        ]
    ],
    "menu_order": 0,
    "position": "normal",
    "style": "default",
    "label_placement": "top",
    "instruction_placement": "label",
    "hide_on_screen": "",
    "active": 1,
    "description": "",
    "modified": 1564485247
}